CONTRIBUTORS
LICENSE
MANIFEST.in
README.rst
requirements-docs.txt
requirements-testing.txt
setup.py
docs/Makefile
docs/api.rst
docs/conf.py
docs/index.rst
docs/usage.rst
fiql_parser/__init__.py
fiql_parser/constants.py
fiql_parser/constraint.py
fiql_parser/exceptions.py
fiql_parser/expression.py
fiql_parser/operator.py
fiql_parser/parser.py
fiql_parser.egg-info/PKG-INFO
fiql_parser.egg-info/SOURCES.txt
fiql_parser.egg-info/dependency_links.txt
fiql_parser.egg-info/top_level.txt
tests/test_objects.py
tests/test_parse.py
tests/test_regex.py